3-files/binary_to_bcd.vhd
library ieee;
use ieee.std_logic_1164.all;
use ieee.numeric_std.all;

entity binary_to_bcd is
  generic (
    bits   : integer := 8;
    digits : integer := 3
  );
  port (
    clk     : in  std_logic;
    reset   : in  std_logic;
    ena     : in  std_logic;
    binary  : in  std_logic_vector(bits-1 downto 0);
    busy    : out std_logic;
    bcd     : out std_logic_vector(digits*4-1 downto 0)
  );
end entity;

architecture Behavioral of binary_to_bcd is
  type state_type is (idle, convert);
  signal state       : state_type := idle;
  signal binary_reg  : std_logic_vector(bits-1 downto 0);
  signal bcd_reg     : std_logic_vector(digits*4-1 downto 0);
  signal bit_count   : integer range 0 to bits := 0;
begin

  process(clk, reset)
  begin
    if reset = '1' then
      state <= idle;
      binary_reg <= (others => '0');
      bcd_reg <= (others => '0');
      bit_count <= 0;
      busy <= '0';
      bcd <= (others => '0');
    elsif rising_edge(clk) then
      case state is
        when idle =>
          busy <= '0';
          if ena = '1' then
            binary_reg <= binary;
            bcd_reg <= (others => '0');
            bit_count <= 0;
            state <= convert;
            busy <= '1';
          end if;

        when convert =>
          for i in 0 to digits-1 loop
            if unsigned(bcd_reg(i*4+3 downto i*4)) >= 5 then
              bcd_reg(i*4+3 downto i*4) <= std_logic_vector(unsigned(bcd_reg(i*4+3 downto i*4)) + 3);
            end if;
          end loop;

          bcd_reg <= bcd_reg(digits*4-2 downto 0) & binary_reg(bits-1);
          binary_reg <= binary_reg(bits-2 downto 0) & '0';

          bit_count <= bit_count + 1;
          if bit_count = bits-1 then
            state <= idle;
            busy <= '0';
            bcd <= bcd_reg(digits*4-2 downto 0) & binary_reg(bits-1);
          end if;
      end case;
    end if;
  end process;

end Behavioral;

2-testbenches/tb_bin_to_bcd.vhd
LIBRARY ieee;
USE ieee.std_logic_1164.ALL;
USE ieee.numeric_std.ALL;

ENTITY tb_binary_to_bcd IS
END tb_binary_to_bcd;

ARCHITECTURE behavior OF tb_binary_to_bcd IS

  COMPONENT binary_to_bcd
    GENERIC (
      bits   : INTEGER := 4;
      digits : INTEGER := 2
    );
    PORT (
      clk     : IN  STD_LOGIC;
      reset   : IN  STD_LOGIC; 
      ena     : IN  STD_LOGIC;
      binary  : IN  STD_LOGIC_VECTOR(bits - 1 DOWNTO 0);
      bcd     : OUT STD_LOGIC_VECTOR(digits * 4 - 1 DOWNTO 0);
      busy    : OUT STD_LOGIC
    );
  END COMPONENT;

  -- Clock
  SIGNAL clk        : STD_LOGIC := '0';
  SIGNAL reset      : STD_LOGIC := '0'; 

  -- Lvl
  SIGNAL level_ena      : STD_LOGIC := '0';
  SIGNAL level_binary   : STD_LOGIC_VECTOR(3 DOWNTO 0) := (OTHERS => '0');
  SIGNAL level_bcd      : STD_LOGIC_VECTOR(7 DOWNTO 0);
  SIGNAL level_busy     : STD_LOGIC;

  -- Score
  SIGNAL score_ena      : STD_LOGIC := '0';
  SIGNAL score_binary   : STD_LOGIC_VECTOR(3 DOWNTO 0) := (OTHERS => '0');
  SIGNAL score_bcd      : STD_LOGIC_VECTOR(7 DOWNTO 0);
  SIGNAL score_busy     : STD_LOGIC;

  CONSTANT clk_period : TIME := 10 ns;

BEGIN

  -- Clock process
  clk_process : PROCESS
  BEGIN
    WHILE NOW < 3000 ns LOOP
      clk <= '0';
      WAIT FOR clk_period / 2;
      clk <= '1';
      WAIT FOR clk_period / 2;
    END LOOP;
    WAIT;
  END PROCESS;

  -- Instantiation 1: lvl
  level_converter : binary_to_bcd
    GENERIC MAP (
      bits   => 4,
      digits => 2
    )
    PORT MAP (
      clk     => clk,
      reset   => reset,
      ena     => level_ena,
      binary  => level_binary,
      bcd     => level_bcd,
      busy    => level_busy
    );

  -- Instantiation 2: score
  score_converter : binary_to_bcd
    GENERIC MAP (
      bits   => 4,
      digits => 2
    )
    PORT MAP (
      clk     => clk,
      reset   => reset,
      ena     => score_ena,
      binary  => score_binary,
      bcd     => score_bcd,
      busy    => score_busy
    );


  stim_proc: PROCESS
  BEGIN
    -- Reset
    reset <= '1';
    WAIT FOR 100 ns;
    reset <= '0';
    WAIT FOR 50 ns;

    -- livello = 1, punteggio = 9
    level_binary  <= "0001";  
    score_binary  <= "1001";  


    level_ena <= '1';
    score_ena <= '1';
    WAIT FOR clk_period;
    level_ena <= '0';
    score_ena <= '0';


    WAIT UNTIL level_busy = '0' AND score_busy = '0';
    WAIT FOR 100 ns;

    WAIT;
  END PROCESS;

END behavior;

1-waves/binn_wave.vcd
$date
  Tue Apr 29 12:46:10 2025
$end
$version
  GHDL v0
$end
$timescale
  1 fs
$end
$scope module standard $end
$upscope $end
$scope module std_logic_1164 $end
$upscope $end
$scope module numeric_std $end
$upscope $end
$scope module tb_binary_to_bcd $end
$var reg 1 ! clk $end
$var reg 1 " reset $end
$var reg 1 # level_ena $end
$var reg 4 $ level_binary[3:0] $end
$var reg 8 % level_bcd[7:0] $end
$var reg 1 & level_busy $end
$var reg 1 ' score_ena $end
$var reg 4 ( score_binary[3:0] $end
$var reg 8 ) score_bcd[7:0] $end
$var reg 1 * score_busy $end
$scope module level_converter $end
$var reg 1 + clk $end
$var reg 1 , reset $end
$var reg 1 - ena $end
$var reg 4 . binary[3:0] $end
$var reg 1 / busy $end
$var reg 8 0 bcd[7:0] $end
$comment state is not handled $end
$var reg 4 1 binary_reg[3:0] $end
$var reg 8 2 bcd_reg[7:0] $end
$var integer 32 3 bit_count $end
$upscope $end
$scope module score_converter $end
$var reg 1 4 clk $end
$var reg 1 5 reset $end
$var reg 1 6 ena $end
$var reg 4 7 binary[3:0] $end
$var reg 1 8 busy $end
$var reg 8 9 bcd[7:0] $end
$comment state is not handled $end
$var reg 4 : binary_reg[3:0] $end
$var reg 8 ; bcd_reg[7:0] $end
$var integer 32 < bit_count $end
$upscope $end
$upscope $end
$enddefinitions $end
#0
0!
1"
0#
b0000 $
b00000000 %
0&
0'
b0000 (
b00000000 )
0*
0+
1,
0-
b0000 .
0/
b00000000 0
b0000 1
b00000000 2
b0 3
04
15
06
b0000 7
08
b00000000 9
b0000 :
b00000000 ;
b0 <
#5000000
1!
1+
14
#10000000
0!
0+
04
#15000000
1!
1+
14
#20000000
0!
0+
04
#25000000
1!
1+
14
#30000000
0!
0+
04
#35000000
1!
1+
14
#40000000
0!
0+
04
#45000000
1!
1+
14
#50000000
0!
0+
04
#55000000
1!
1+
14
#60000000
0!
0+
04
#65000000
1!
1+
14
#70000000
0!
0+
04
#75000000
1!
1+
14
#80000000
0!
0+
04
#85000000
1!
1+
14
#90000000
0!
0+
04
#95000000
1!
1+
14
#100000000
0!
0"
0+
0,
04
05
#105000000
1!
1+
14
#110000000
0!
0+
04
#115000000
1!
1+
14
#120000000
0!
0+
04
#125000000
1!
1+
14
#130000000
0!
0+
04
#135000000
1!
1+
14
#140000000
0!
0+
04
#145000000
1!
1+
14
#150000000
0!
1#
b0001 $
1'
b1001 (
0+
1-
b0001 .
04
16
b1001 7
#155000000
1!
1&
1*
1+
1/
b0001 1
14
18
b1001 :
#160000000
0!
0#
0'
0+
0-
04
06
#165000000
1!
1+
b0010 1
b1 3
14
b0010 :
b00000001 ;
b1 <
#170000000
0!
0+
04
#175000000
1!
1+
b0100 1
b10 3
14
b0100 :
b00000010 ;
b10 <
#180000000
0!
0+
04
#185000000
1!
1+
b1000 1
b11 3
14
b1000 :
b00000100 ;
b11 <
#190000000
0!
0+
04
#195000000
1!
b00000001 %
0&
b00001001 )
0*
1+
0/
b00000001 0
b0000 1
b00000001 2
b100 3
14
08
b00001001 9
b0000 :
b00001001 ;
b100 <
