3-files/control_unit.vhd
library ieee;
use ieee.std_logic_1164.all;
use ieee.numeric_std.all;

entity control_unit is
  generic (
    DELAY_CYCLES : integer := 100000000
  );
  port (
    clk                : in  std_logic;
    reset              : in  std_logic;
    center_btn         : in  std_logic;
    done_patt          : in  std_logic;
    score_valid        : in  std_logic;
    level_up           : in  std_logic;
    repeat_level       : in  std_logic;
    all_switches_down  : in  std_logic;
    level              : out std_logic_vector(1 downto 0);
    ones_count         : out std_logic_vector(3 downto 0);
    enable_patt        : out std_logic;
    start_compare      : out std_logic;
    led_mode           : out std_logic_vector(1 downto 0); -- "00"=OFF, "01"=BLINK, "10"=SHOW
    state_out          : out std_logic_vector(4 downto 0) -- For debugging
  );
end control_unit;

architecture Behavioral of control_unit is

  type state_type is (
    idle, blink_all, generate_pattern, wait_pattern_done,
    show_pattern_once, wait_for_btn_eval, show_pattern_again,
    wait_score, wait_switches_down, delay_after_clear,
    check_score, next_level
  );

  signal state              : state_type := idle;
  signal next_state         : state_type;
  signal level_reg          : std_logic_vector(1 downto 0) := "00";
  signal delay_counter      : integer range 0 to DELAY_CYCLES := 0;
  signal blink_counter      : integer range 0 to 6 := 0;
  signal ones_count_reg     : std_logic_vector(3 downto 0) := (others => '0');
  signal level_up_reg       : std_logic := '0';
  signal repeat_level_reg   : std_logic := '0';
  signal switches_down_reg  : std_logic := '0';
  signal score_valid_reg    : std_logic := '0';

begin

  -- Synchronous process
  process(clk, reset)
  begin
    if reset = '1' then
      state <= idle;
      level_reg <= "00";
      delay_counter <= 0;
      blink_counter <= 0;
      ones_count_reg <= (others => '0');
      level_up_reg <= '0';
      repeat_level_reg <= '0';
      switches_down_reg <= '0';
      score_valid_reg <= '0';

    elsif rising_edge(clk) then
      state <= next_state;

      -- Capture signals
      if state = wait_score and score_valid = '1' then
        level_up_reg <= level_up;
        repeat_level_reg <= repeat_level;
        score_valid_reg <= '1';

        -- Sicurezza extra
        if (level_up = '1' and repeat_level = '1') then
          assert false report "Errore: sia level_up che repeat_level sono alti contemporaneamente!" severity failure;
        elsif (level_up = '0' and repeat_level = '0') then
          assert false report "Errore: né level_up né repeat_level sono alti con score_valid=1!" severity failure;

        end if;

      end if;


      if state = check_score and next_state /= check_score then
        score_valid_reg <= '0';
        level_up_reg <= '0';
        repeat_level_reg <= '0';
      end if;
        
      switches_down_reg <= all_switches_down;


      -- Delay counter
      if state = show_pattern_once or state = delay_after_clear then
        if delay_counter < DELAY_CYCLES then
          delay_counter <= delay_counter + 1;
        end if;
      else
        delay_counter <= 0;
      end if;

      -- Blink counter
      if state = blink_all then
        if blink_counter < 6 then
          blink_counter <= blink_counter + 1;
        end if;
      else
        blink_counter <= 0;
      end if;

      -- Update level
      if state = check_score and level_up_reg = '1' then
        if level_reg < "10" then
          level_reg <= std_logic_vector(unsigned(level_reg) + 1);
        end if;
      end if;

      -- Update ones_count
      if state = generate_pattern then
        if level_reg = "00" then
          ones_count_reg <= "0110"; -- 6
        else
          ones_count_reg <= "1000"; -- 8
        end if;
      end if;
    end if;
  end process;

  -- FSM process
  process(state, center_btn, done_patt, score_valid_reg, level_up_reg, switches_down_reg, delay_counter, blink_counter, repeat_level_reg)
  begin
    next_state     <= state;
    enable_patt    <= '0';
    start_compare  <= '0';
    led_mode       <= "00";

    case state is
      when idle =>
        if center_btn = '1' then
          next_state <= blink_all after 1 ns;
        end if;

      when blink_all =>
        led_mode <= "01";
        if blink_counter = 6 then
          next_state <= generate_pattern;
        end if;

      when generate_pattern =>
        enable_patt <= '1';
        next_state <= wait_pattern_done;

      when wait_pattern_done =>
        if done_patt = '1' then
          next_state <= show_pattern_once;
        end if;

      when show_pattern_once =>
        led_mode <= "10";
        if delay_counter >= DELAY_CYCLES then
          next_state <= wait_for_btn_eval;
        end if;

      when wait_for_btn_eval =>
        led_mode <= "00";
        if center_btn = '1' then
          next_state <= show_pattern_again;
        end if;

      when show_pattern_again =>
        led_mode <= "10";
        start_compare <= '1';
        next_state <= wait_score;

      when wait_score =>
        led_mode <= "10";
        if score_valid = '1' then
          next_state <= wait_switches_down;
        end if;

      when wait_switches_down =>
        led_mode <= "10";
        if switches_down_reg = '1' then
          led_mode <= "00";
          next_state <= delay_after_clear;
        end if;

      when delay_after_clear =>
        if delay_counter >= DELAY_CYCLES then
          next_state <= check_score;
        end if;

      when check_score =>
          if level_up_reg = '1' then
            next_state <= next_level;
          elsif repeat_level_reg = '1' then
            next_state <= generate_pattern;
          end if;

      when next_level =>
        next_state <= blink_all;
    end case;
  end process;

  -- Output mapping
  level <= level_reg;
  ones_count <= ones_count_reg;
  state_out <= std_logic_vector(to_unsigned(state_type'pos(state), 5));

end Behavioral;

2-testbenches/tb_control_unit.vhd
library ieee;
use ieee.std_logic_1164.all;
use ieee.numeric_std.all;

entity tb_control_unit is
end tb_control_unit;

architecture behavior of tb_control_unit is

  component control_unit
    generic (
      DELAY_CYCLES : integer := 5
    );
    port (
      clk               : in  std_logic;
      reset             : in  std_logic;
      center_btn        : in  std_logic;
      done_patt         : in  std_logic;
      score_valid       : in  std_logic;
      level_up          : in  std_logic;
      repeat_level      : in  std_logic;
      all_switches_down : in  std_logic;

      level             : out std_logic_vector(1 downto 0);
      ones_count        : out std_logic_vector(3 downto 0);
      enable_patt       : out std_logic;
      start_compare     : out std_logic;
      led_mode          : out std_logic_vector(1 downto 0);
      state_out         : out std_logic_vector(4 downto 0)
    );
  end component;

  signal clk_tb               : std_logic := '0';
  signal reset_tb             : std_logic := '1';
  signal center_btn_tb        : std_logic := '0';
  signal done_patt_tb         : std_logic := '0';
  signal score_valid_tb       : std_logic := '0';
  signal level_up_tb          : std_logic := '0';
  signal repeat_level_tb      : std_logic := '0';
  signal all_switches_down_tb : std_logic := '0';

  signal level_tb             : std_logic_vector(1 downto 0);
  signal ones_count_tb        : std_logic_vector(3 downto 0);
  signal enable_patt_tb       : std_logic;
  signal start_compare_tb     : std_logic;
  signal led_mode_tb          : std_logic_vector(1 downto 0);
  signal state_out_tb         : std_logic_vector(4 downto 0);

  constant clk_period : time := 10 ns;

begin

  -- Clock generator
  clk_process : process
  begin
    loop
      clk_tb <= '0'; wait for clk_period / 2;
      clk_tb <= '1'; wait for clk_period / 2;
    end loop;
  end process;

  uut: control_unit
    generic map (
      DELAY_CYCLES => 5
    )
    port map (
      clk                => clk_tb,
      reset              => reset_tb,
      center_btn         => center_btn_tb,
      done_patt          => done_patt_tb,
      score_valid        => score_valid_tb,
      level_up           => level_up_tb,
      repeat_level       => repeat_level_tb,
      all_switches_down  => all_switches_down_tb,
      level              => level_tb,
      ones_count         => ones_count_tb,
      enable_patt        => enable_patt_tb,
      start_compare      => start_compare_tb,
      led_mode           => led_mode_tb,
      state_out          => state_out_tb
    );

    stim_proc : process
    begin
        -- Reset
        reset_tb <= '1';
        wait for 20 ns;
        reset_tb <= '0';
        wait for 20 ns;
    
        -- Inizio gioco (center button premuto)
        center_btn_tb <= '1';
        wait for clk_period;
        center_btn_tb <= '0';
    
        -- Aspetta che venga abilitato il generatore pattern
        wait until enable_patt_tb = '1';
        wait for clk_period;
    
        -- Simula fine generazione pattern
        done_patt_tb <= '1';
        wait for clk_period;
        done_patt_tb <= '0';
    
        -- Attesa per simulare player pronto
        wait for 50 ns;
        center_btn_tb <= '1';
        wait for 2*clk_period;
        center_btn_tb <= '0';
    
        -- Aspetta che parta il confronto
        wait until start_compare_tb = '1';
        wait for clk_period;
        score_valid_tb <= '1';

        -- Level Up Check         **(happens while score_valid is true in datapath)**

         level_up_tb <= '1'; -- normalmente arriva repeat level ma ora testiamo level up
         wait for 2*clk_period; -- almeno 2 clock! altrimenti la control unit non recepisce!
         level_up_tb <= '0';


        --  Repeat Level Check

        -- repeat_level_tb <= '1';
        -- wait for 2*clk_period; -- almeno 2 clock! 
        -- repeat_level_tb <= '0';


        score_valid_tb <= '0';
    
        -- Simula che il giocatore ha abbassato gli switch
        wait for 30 ns;
        all_switches_down_tb <= '1';
        wait for 3 * clk_period;
        all_switches_down_tb <= '0';
  
    
        -- Fine test
        wait until state_out_tb = "00001";
        report "Test completato. Finito primo livello";
        assert false report "Fine simulazione." severity failure;
    end process;

  -- Timeout per evitare loop infiniti
  end_sim_proc : process
  begin
    wait for 700 ns;
    assert false report "Timeout raggiunto (700ns). Simulazione interrotta." severity failure;
  end process;

  -- Processo di monitoraggio dello stato
  monitor_state_proc : process(clk_tb)
begin
  if rising_edge(clk_tb) then
    case to_integer(unsigned(state_out_tb)) is
      when 0 => report "Stato: idle";
      when 1 => report "Stato: blink_all";
      when 2 => report "Stato: generate_pattern";
      when 3 => report "Stato: wait_pattern_done";
      when 4 => report "Stato: show_pattern_once";
      when 5 => report "Stato: wait_for_btn_eval";
      when 6 => report "Stato: show_pattern_again";
      when 7 => report "Stato: wait_score";
      when 8 => report "Stato: wait_switches_down";
      when 9 => report "Stato: delay_after_clear";
      when 10 => report "Stato: check_score";
      when 11 => report "Stato: next_level";
      when others => report "Stato: sconosciuto!";
    end case;
  end if;
end process;

end behavior;

1-waves/control_wave.vcd
$date
  Sat Apr 26 15:22:17 2025
$end
$version
  GHDL v0
$end
$timescale
  1 fs
$end
$scope module standard $end
$upscope $end
$scope module std_logic_1164 $end
$upscope $end
$scope module numeric_std $end
$upscope $end
$scope module tb_control_unit $end
$var reg 1 ! clk_tb $end
$var reg 1 " reset_tb $end
$var reg 1 # center_btn_tb $end
$var reg 1 $ done_patt_tb $end
$var reg 1 % score_valid_tb $end
$var reg 1 & level_up_tb $end
$var reg 1 ' repeat_level_tb $end
$var reg 1 ( all_switches_down_tb $end
$var reg 2 ) level_tb[1:0] $end
$var reg 4 * ones_count_tb[3:0] $end
$var reg 1 + enable_patt_tb $end
$var reg 1 , start_compare_tb $end
$var reg 2 - led_mode_tb[1:0] $end
$var reg 5 . state_out_tb[4:0] $end
$scope module uut $end
$var reg 1 / clk $end
$var reg 1 0 reset $end
$var reg 1 1 center_btn $end
$var reg 1 2 done_patt $end
$var reg 1 3 score_valid $end
$var reg 1 4 level_up $end
$var reg 1 5 repeat_level $end
$var reg 1 6 all_switches_down $end
$var reg 2 7 level[1:0] $end
$var reg 4 8 ones_count[3:0] $end
$var reg 1 9 enable_patt $end
$var reg 1 : start_compare $end
$var reg 2 ; led_mode[1:0] $end
$var reg 5 < state_out[4:0] $end
$comment state is not handled $end
$comment next_state is not handled $end
$var reg 2 = level_reg[1:0] $end
$var integer 32 > delay_counter $end
$var integer 32 ? blink_counter $end
$var reg 4 @ ones_count_reg[3:0] $end
$var reg 1 A level_up_reg $end
$var reg 1 B repeat_level_reg $end
$var reg 1 C switches_down_reg $end
$var reg 1 D score_valid_reg $end
$upscope $end
$upscope $end
$enddefinitions $end
#0
0!
1"
0#
0$
0%
0&
0'
0(
b00 )
b0000 *
0+
0,
b00 -
b00000 .
0/
10
01
02
03
04
05
06
b00 7
b0000 8
09
0:
b00 ;
b00000 <
b00 =
b0 >
b0 ?
b0000 @
0A
0B
0C
0D
#5000000
1!
1/
#10000000
0!
0/
#15000000
1!
1/
#20000000
0!
0"
0/
00
#25000000
1!
1/
#30000000
0!
0/
#35000000
1!
1/
#40000000
0!
1#
0/
11
#45000000
1!
b01 -
b00001 .
1/
b01 ;
b00001 <
#50000000
0!
0#
0/
01
b01 ;
#55000000
1!
1/
b01 ;
b1 ?
#60000000
0!
0/
#65000000
1!
1/
b01 ;
b10 ?
#70000000
0!
0/
#75000000
1!
1/
b01 ;
b11 ?
#80000000
0!
0/
#85000000
1!
1/
b01 ;
b100 ?
#90000000
0!
0/
#95000000
1!
1/
b01 ;
b101 ?
#100000000
0!
0/
#105000000
1!
1/
b01 ;
b110 ?
#110000000
0!
0/
#115000000
1!
1+
b00 -
b00010 .
1/
19
b00 ;
b00010 <
#120000000
0!
0/
#125000000
1!
1$
b0110 *
0+
b00011 .
1/
12
b0110 8
09
b00011 <
b0 ?
b0110 @
#130000000
0!
0/
#135000000
1!
0$
b10 -
b00100 .
1/
02
b10 ;
b00100 <
#140000000
0!
0/
#145000000
1!
1/
b10 ;
b1 >
#150000000
0!
0/
#155000000
1!
1/
b10 ;
b10 >
#160000000
0!
0/
#165000000
1!
1/
b10 ;
b11 >
#170000000
0!
0/
#175000000
1!
1/
b10 ;
b100 >
#180000000
0!
0/
#185000000
1!
1#
1/
11
b10 ;
b101 >
#190000000
0!
0/
#195000000
1!
b00 -
b00101 .
1/
b00 ;
b00101 <
#200000000
0!
0/
#205000000
1!
0#
1,
b10 -
b00110 .
1/
01
1:
b10 ;
b00110 <
b0 >
#210000000
0!
0/
#215000000
1!
1%
1&
0,
b00111 .
1/
13
14
0:
b10 ;
b00111 <
#220000000
0!
0/
#225000000
1!
b01000 .
1/
b10 ;
b01000 <
1A
1D
#230000000
0!
0/
#235000000
1!
0%
0&
1/
03
04
#240000000
0!
0/
#245000000
1!
1/
#250000000
0!
0/
#255000000
1!
1/
#260000000
0!
0/
#265000000
1!
1(
b00 -
1/
16
b00 ;
1C
#270000000
0!
0/
#275000000
1!
b01001 .
1/
b01001 <
#280000000
0!
0/
#285000000
1!
1/
b1 >
#290000000
0!
0/
#295000000
1!
0(
1/
06
b10 >
0C
#300000000
0!
0/
#305000000
1!
1/
b11 >
#310000000
0!
0/
#315000000
1!
1/
b100 >
#320000000
0!
0/
#325000000
1!
1/
b101 >
#330000000
0!
0/
#335000000
1!
b01010 .
1/
b01010 <
#340000000
0!
0/
#345000000
1!
b01 )
b01011 .
1/
b01 7
b01011 <
b01 =
b0 >
0A
0D
