3-files/debouncer.vhd
library ieee;
use ieee.std_logic_1164.all;
use ieee.numeric_std.all;

entity debouncer is
  generic (
    counter_size : integer := 12
  );
  port (
    clock  : in std_logic;
    reset  : in std_logic;
    bouncy : in std_logic;
    pulse  : out std_logic
  );
end debouncer;

architecture behavioral of debouncer is

  signal counter         : unsigned(counter_size - 1 downto 0) := (others => '1');
  signal candidate_value : std_logic := '0';
  signal stable_value    : std_logic := '0';
  signal pulse_reg       : std_logic := '0';
  signal prev_stable     : std_logic := '0';

begin

  process(clock, reset)
  begin
    if reset = '1' then
      counter         <= (others => '1');
      candidate_value <= '0';
      stable_value    <= '0';
      pulse_reg       <= '0';
      prev_stable     <= '0';

    elsif rising_edge(clock) then
      pulse_reg <= '0'; -- default, unless explicitly raised

      -- Debouncing logic
      if bouncy = candidate_value then
        if counter = 0 then
          if stable_value /= candidate_value then
            stable_value <= candidate_value;
          end if;
        else
          counter <= counter - 1;
        end if;
      else
        candidate_value <= bouncy;
        counter <= (others => '1');
      end if;

      -- Pulse generation only on stable 0->1 edge
      if stable_value = '1' and prev_stable = '0' then
        pulse_reg <= '1';
      end if;

      -- Update previous stable value
      prev_stable <= stable_value;
    end if;
  end process;

  pulse <= pulse_reg;

end behavioral;

2-testbenches/tb_debouncer.vhd
library IEEE;
use IEEE.STD_LOGIC_1164.ALL;

entity tb_debouncer is
--  Port ( );
end tb_debouncer;

architecture Behavioral of tb_debouncer is

component debouncer 
  generic (
    counter_size : integer := 2 -- with 2, it takes 55 ns to detect a pulse and get's updated at the next clock rise
  );
  port (
    clock, reset : in std_logic;
    bouncy : in std_logic;
    pulse : out std_logic
  );
end component;

signal clock : std_logic := '0';
signal reset : std_logic := '0';
signal bouncy : std_logic := '0';
signal pulse : std_logic := '0';

begin
    -- dut instantiator, uses the internal signal to mimic hardware's
   dut : debouncer
   port map(
      clock  => clock,
      reset  => reset,
      bouncy => bouncy,
      pulse   => pulse
   );

   clock <= not(clock) after 5 ns;

   dut_test_proc : process
   begin

      reset <= '1';
      wait for 10 ns;
      reset <= '0';
      wait for 10 ns;

      --Simulates a quick bounce — a press that's too fast to be considered stable.

      bouncy <= '0';
      wait for 10 ns;

      bouncy <= '1';
      wait for 10 ns;

      bouncy <= '0';
      wait for 10 ns;

      bouncy <= '1';
      wait for 15 ns;

        -- this one is long enough for a second pulse to be generated 
      bouncy <= '0';
      wait for 10 ns;

      bouncy <= '1';
      wait for 75 ns;
      bouncy <= '0';

      wait for 50 ns;
      bouncy <= '1';
      wait for 300 ns;  -- ensure longer than debounce count
      bouncy <= '0';

      wait;
      end process;
   
      -- Stop simulation after a while
      end_sim_proc : process
      begin
         wait for 900 ns;
         assert false report "Simulation finished after 900ns." severity failure;
      end process;

end Behavioral;

1-waves/deb3_wave.vcd
$date
  Fri Apr 25 16:27:55 2025
$end
$version
  GHDL v0
$end
$timescale
  1 fs
$end
$scope module standard $end
$upscope $end
$scope module std_logic_1164 $end
$upscope $end
$scope module numeric_std $end
$upscope $end
$scope module tb_debouncer $end
$var reg 1 ! clock $end
$var reg 1 " reset $end
$var reg 1 # bouncy $end
$var reg 1 $ pulse $end
$scope module dut $end
$var reg 1 % clock $end
$var reg 1 & reset $end
$var reg 1 ' bouncy $end
$var reg 1 ( pulse $end
$var reg 2 ) counter[1:0] $end
$var reg 1 * candidate_value $end
$var reg 1 + stable_value $end
$var reg 1 , pulse_reg $end
$var reg 1 - prev_stable $end
$upscope $end
$upscope $end
$enddefinitions $end
#0
0!
1"
0#
0$
0%
1&
0'
0(
b11 )
0*
0+
0,
0-
#5000000
1!
1%
#10000000
0!
0"
0%
0&
#15000000
1!
1%
b10 )
#20000000
0!
0%
#25000000
1!
1%
b01 )
#30000000
0!
1#
0%
1'
#35000000
1!
1%
b11 )
1*
#40000000
0!
0#
0%
0'
#45000000
1!
1%
0*
#50000000
0!
1#
0%
1'
#55000000
1!
1%
1*
#60000000
0!
0%
#65000000
1!
0#
1%
0'
b10 )
#70000000
0!
0%
#75000000
1!
1#
1%
1'
b11 )
0*
#80000000
0!
0%
#85000000
1!
1%
1*
#90000000
0!
0%
#95000000
1!
1%
b10 )
#100000000
0!
0%
#105000000
1!
1%
b01 )
#110000000
0!
0%
#115000000
1!
1%
b00 )
#120000000
0!
0%
#125000000
1!
1%
1+
#130000000
0!
0%
#135000000
1!
1$
1%
1(
1,
1-
#140000000
0!
0%
#145000000
1!
0$
1%
0(
0,
#150000000
0!
0#
0%
0'
#155000000
1!
1%
b11 )
0*
#160000000
0!
0%
#165000000
1!
1%
b10 )
#170000000
0!
0%
#175000000
1!
1%
b01 )
#180000000
0!
0%
#185000000
1!
1%
b00 )
#190000000
0!
0%
#195000000
1!
1%
0+
#200000000
0!
1#
0%
1'
#205000000
1!
1%
b11 )
1*
0-
#210000000
0!
0%
#215000000
1!
1%
b10 )
#220000000
0!
0%
#225000000
1!
1%
b01 )
#230000000
0!
0%
#235000000
1!
1%
b00 )
#240000000
0!
0%
#245000000
1!
1%
1+
#250000000
0!
0%
#255000000
1!
1$
1%
1(
1,
1-
#260000000
0!
0%
#265000000
1!
0$
1%
0(
0,
