3-files/datapath.vhd
library ieee;
use ieee.std_logic_1164.all;
use ieee.numeric_std.all;

entity datapath is
  port (
    clk          : in  std_logic;
    reset        : in  std_logic;
    start_compare: in  std_logic;  -- segnale per iniziare confronto
    level        : in  std_logic_vector(1 downto 0); -- 2-bit: 00=liv1, 01=liv2, 10=liv3
    pattern_in   : in  std_logic_vector(15 downto 0);
    switches     : in  std_logic_vector(15 downto 0);
    score        : out std_logic_vector(3 downto 0);
    score_valid  : out std_logic;  -- 1 clock dopo il confronto
    level_up     : out std_logic;
    repeat_level : out std_logic
  );
end datapath;

architecture Behavioral of datapath is

  type state_type is (idle, compare, done);
  signal state         : state_type := idle;

  signal pattern_reg   : std_logic_vector(15 downto 0) := (others => '0');
  signal switches_reg  : std_logic_vector(15 downto 0) := (others => '0');
  signal score_reg     : integer range 0 to 15 := 0;
  signal temp_score    : integer range -16 to 32 := 0;
  signal bit_index     : integer range 0 to 15 := 0;
  signal level_up_int  : std_logic := '0';
  signal repeat_level_int : std_logic := '0';
  signal score_valid_int  : std_logic := '0';

begin

  process(clk, reset)
  begin
    if reset = '1' then
      state        <= idle;
      score_reg    <= 0;
      score_valid_int  <= '0';
      pattern_reg  <= (others => '0');
      switches_reg <= (others => '0');
      bit_index    <= 0;
      temp_score   <= 0;
      level_up_int <= '0';
      repeat_level_int <= '0';

    elsif rising_edge(clk) then
      case state is

        when idle =>
          score_valid_int <= '0';
          level_up_int <= '0';
          repeat_level_int <= '0';

          if start_compare = '1' then
            pattern_reg  <= pattern_in;
            switches_reg <= switches;
            bit_index    <= 0;
            temp_score   <= 0;
            score_reg    <= 0;
            state        <= compare;
          end if;

        when compare =>
          -- confronto singolo bit per ciclo
          if pattern_reg(bit_index) = '1' and switches_reg(bit_index) = '1' then
            temp_score <= temp_score + 1;
          elsif pattern_reg(bit_index) = '0' and switches_reg(bit_index) = '1' then
            temp_score <= temp_score - 1;
          elsif pattern_reg(bit_index) = '1' and switches_reg(bit_index) = '0' and level = "10" then -- livello 3
            temp_score <= temp_score - 1;
          end if;

          if bit_index = 15 then
            state <= done;
          else
            bit_index <= bit_index + 1;
          end if;

        when done =>
          -- clamp e update
          if temp_score < 0 then
            score_reg <= 0;
            level_up_int <= '0';
            repeat_level_int <= '1';
          elsif temp_score >= 16 then
            score_reg <= 15;
            level_up_int <= '1';
            repeat_level_int <= '0';
          else
            score_reg <= temp_score;
            level_up_int <= '0';
            repeat_level_int <= '1';
          end if;

          score_valid_int <= '1';
          state <= idle;
      end case;
    end if;
  end process;

  score <= std_logic_vector(to_unsigned(score_reg, 4));
  score_valid <= score_valid_int;
  level_up <= level_up_int;
  repeat_level <= repeat_level_int;

end Behavioral;

2-testbenches/tb_datapath.vhd
library ieee;
use ieee.std_logic_1164.all;
use ieee.numeric_std.all;

entity tb_datapath is
end tb_datapath;

architecture behavior of tb_datapath is

  component datapath
    port (
      clk          : in  std_logic;
      reset        : in  std_logic;
      start_compare: in  std_logic;
      level        : in  std_logic_vector(1 downto 0);
      pattern_in   : in  std_logic_vector(15 downto 0);
      switches     : in  std_logic_vector(15 downto 0);
      score        : out std_logic_vector(3 downto 0);
      score_valid  : out std_logic;
      level_up     : out std_logic;
      repeat_level : out std_logic
    );
  end component;

  signal clk_tb          : std_logic := '0';
  signal reset_tb        : std_logic := '1';
  signal start_compare_tb: std_logic := '0';
  signal level_tb        : std_logic_vector(1 downto 0) := (others => '0');
  signal pattern_in_tb   : std_logic_vector(15 downto 0) := (others => '0');
  signal switches_tb     : std_logic_vector(15 downto 0) := (others => '0');
  signal score_tb        : std_logic_vector(3 downto 0);
  signal score_valid_tb  : std_logic;
  signal level_up_tb     : std_logic;
  signal repeat_level_tb     : std_logic;

  constant clk_period : time := 10 ns;

begin

  clk_process : process
  begin
    while now < 1000 ns loop
      clk_tb <= '0'; wait for clk_period / 2;
      clk_tb <= '1'; wait for clk_period / 2;
    end loop;
    wait;
  end process;

  uut: datapath
    port map (
      clk           => clk_tb,
      reset         => reset_tb,
      start_compare => start_compare_tb,
      level         => level_tb,
      pattern_in    => pattern_in_tb,
      switches      => switches_tb,
      score         => score_tb,
      score_valid   => score_valid_tb,
      level_up      => level_up_tb,
      repeat_level => repeat_level_tb

    );

  stim_proc: process
  begin
    reset_tb <= '1';
    wait for 50 ns;
    reset_tb <= '0';
    wait for 20 ns;

    ----------------------------------------------------
    -- Test livello 1: 3 giusti, 1 mancante
    ----------------------------------------------------
    level_tb <= "00";  -- livello 1
    pattern_in_tb <= x"00F0";
    switches_tb   <= x"00E0";  -- uno mancante
    start_compare_tb <= '1'; wait for clk_period; start_compare_tb <= '0';
    wait until score_valid_tb = '1'; wait for clk_period;

    ----------------------------------------------------
    -- Test livello 2: 4 giusti, 1 sbagliato
    ----------------------------------------------------
    level_tb <= "01";  -- livello 2
    pattern_in_tb <= x"F000";
    switches_tb   <= x"F001";
    start_compare_tb <= '1'; wait for clk_period; start_compare_tb <= '0';
    wait until score_valid_tb = '1'; wait for clk_period;

    ----------------------------------------------------
    -- Test livello 3: 4 mancati → penalizzati
    ----------------------------------------------------
    level_tb <= "10";  -- livello 3
    pattern_in_tb <= x"0F01";
    switches_tb   <= x"0E00";
    start_compare_tb <= '1'; wait for clk_period; start_compare_tb <= '0';
    wait until score_valid_tb = '1'; wait for clk_period;

    ----------------------------------------------------
    -- Test livello 3: score oltre 16
    ----------------------------------------------------
    level_tb <= "10";
    pattern_in_tb <= x"FFFF";
    switches_tb   <= x"FFFF";
    start_compare_tb <= '1'; wait for clk_period; start_compare_tb <= '0';
    wait until score_valid_tb = '1'; wait for clk_period;

    report "Test completato.";
    assert false report "Fine simulazione." severity failure;
  end process;

end behavior;

1-waves/final_datap_wave.vcd
$date
  Sat Apr 26 12:56:23 2025
$end
$version
  GHDL v0
$end
$timescale
  1 fs
$end
$scope module standard $end
$upscope $end
$scope module std_logic_1164 $end
$upscope $end
$scope module numeric_std $end
$upscope $end
$scope module tb_datapath $end
$var reg 1 ! clk_tb $end
$var reg 1 " reset_tb $end
$var reg 1 # start_compare_tb $end
$var reg 2 $ level_tb[1:0] $end
$var reg 16 % pattern_in_tb[15:0] $end
$var reg 16 & switches_tb[15:0] $end
$var reg 4 ' score_tb[3:0] $end
$var reg 1 ( score_valid_tb $end
$var reg 1 ) level_up_tb $end
$var reg 1 * repeat_level_tb $end
$scope module uut $end
$var reg 1 + clk $end
$var reg 1 , reset $end
$var reg 1 - start_compare $end
$var reg 2 . level[1:0] $end
$var reg 16 / pattern_in[15:0] $end
$var reg 16 0 switches[15:0] $end
$var reg 4 1 score[3:0] $end
$var reg 1 2 score_valid $end
$var reg 1 3 level_up $end
$var reg 1 4 repeat_level $end
$comment state is not handled $end
$var reg 16 5 pattern_reg[15:0] $end
$var reg 16 6 switches_reg[15:0] $end
$var integer 32 7 score_reg $end
$var integer 32 8 temp_score $end
$var integer 32 9 bit_index $end
$var reg 1 : level_up_int $end
$var reg 1 ; repeat_level_int $end
$var reg 1 < score_valid_int $end
$upscope $end
$upscope $end
$enddefinitions $end
#0
0!
1"
0#
b00 $
b0000000000000000 %
b0000000000000000 &
b0000 '
0(
0)
0*
0+
1,
0-
b00 .
b0000000000000000 /
b0000000000000000 0
b0000 1
02
03
04
b0000000000000000 5
b0000000000000000 6
b0 7
b0 8
b0 9
0:
0;
0<
#5000000
1!
1+
#10000000
0!
0+
#15000000
1!
1+
#20000000
0!
0+
#25000000
1!
1+
#30000000
0!
0+
#35000000
1!
1+
#40000000
0!
0+
#45000000
1!
1+
#50000000
0!
0"
0+
0,
#55000000
1!
1+
#60000000
0!
0+
#65000000
1!
1+
#70000000
0!
1#
b0000000011110000 %
b0000000011100000 &
0+
1-
b0000000011110000 /
b0000000011100000 0
#75000000
1!
1+
b0000000011110000 5
b0000000011100000 6
#80000000
0!
0#
0+
0-
#85000000
1!
1+
b1 9
#90000000
0!
0+
#95000000
1!
1+
b10 9
#100000000
0!
0+
#105000000
1!
1+
b11 9
#110000000
0!
0+
#115000000
1!
1+
b100 9
#120000000
0!
0+
#125000000
1!
1+
b101 9
#130000000
0!
0+
#135000000
1!
1+
b1 8
b110 9
#140000000
0!
0+
#145000000
1!
1+
b10 8
b111 9
#150000000
0!
0+
#155000000
1!
1+
b11 8
b1000 9
#160000000
0!
0+
#165000000
1!
1+
b1001 9
#170000000
0!
0+
#175000000
1!
1+
b1010 9
#180000000
0!
0+
#185000000
1!
1+
b1011 9
#190000000
0!
0+
#195000000
1!
1+
b1100 9
#200000000
0!
0+
#205000000
1!
1+
b1101 9
#210000000
0!
0+
#215000000
1!
1+
b1110 9
#220000000
0!
0+
#225000000
1!
1+
b1111 9
#230000000
0!
0+
#235000000
1!
1+
#240000000
0!
0+
#245000000
1!
b0011 '
1(
1*
1+
b0011 1
12
14
b11 7
1;
1<
#250000000
0!
0+
#255000000
1!
1#
b01 $
b1111000000000000 %
b1111000000000001 &
b0000 '
0(
0*
1+
1-
b01 .
b1111000000000000 /
b1111000000000001 0
b0000 1
02
04
b1111000000000000 5
b1111000000000001 6
b0 7
b0 8
b0 9
0;
0<
#260000000
0!
0+
#265000000
1!
0#
1+
0-
b11111111111111111111111111111111 8
b1 9
#270000000
0!
0+
#275000000
1!
1+
b10 9
#280000000
0!
0+
#285000000
1!
1+
b11 9
#290000000
0!
0+
#295000000
1!
1+
b100 9
#300000000
0!
0+
#305000000
1!
1+
b101 9
#310000000
0!
0+
#315000000
1!
1+
b110 9
#320000000
0!
0+
#325000000
1!
1+
b111 9
#330000000
0!
0+
#335000000
1!
1+
b1000 9
#340000000
0!
0+
#345000000
1!
1+
b1001 9
#350000000
0!
0+
#355000000
1!
1+
b1010 9
#360000000
0!
0+
#365000000
1!
1+
b1011 9
#370000000
0!
0+
#375000000
1!
1+
b1100 9
#380000000
0!
0+
#385000000
1!
1+
b0 8
b1101 9
#390000000
0!
0+
#395000000
1!
1+
b1 8
b1110 9
#400000000
0!
0+
#405000000
1!
1+
b10 8
b1111 9
#410000000
0!
0+
#415000000
1!
1+
b11 8
#420000000
0!
0+
#425000000
1!
b0011 '
1(
1*
1+
b0011 1
12
14
b11 7
1;
1<
#430000000
0!
0+
#435000000
1!
1#
b10 $
b0000111100000001 %
b0000111000000000 &
b0000 '
0(
0*
1+
1-
b10 .
b0000111100000001 /
b0000111000000000 0
b0000 1
02
04
b0000111100000001 5
b0000111000000000 6
b0 7
b0 8
b0 9
0;
0<
#440000000
0!
0+
#445000000
1!
0#
1+
0-
b11111111111111111111111111111111 8
b1 9
#450000000
0!
0+
#455000000
1!
1+
b10 9
#460000000
0!
0+
#465000000
1!
1+
b11 9
#470000000
0!
0+
#475000000
1!
1+
b100 9
#480000000
0!
0+
#485000000
1!
1+
b101 9
#490000000
0!
0+
#495000000
1!
1+
b110 9
#500000000
0!
0+
#505000000
1!
1+
b111 9
#510000000
0!
0+
#515000000
1!
1+
b1000 9
#520000000
0!
0+
#525000000
1!
1+
b11111111111111111111111111111110 8
b1001 9
#530000000
0!
0+
#535000000
1!
1+
b11111111111111111111111111111111 8
b1010 9
#540000000
0!
0+
#545000000
1!
1+
b0 8
b1011 9
#550000000
0!
0+
#555000000
1!
1+
b1 8
b1100 9
#560000000
0!
0+
#565000000
1!
1+
b1101 9
#570000000
0!
0+
#575000000
1!
1+
b1110 9
#580000000
0!
0+
#585000000
1!
1+
b1111 9
#590000000
0!
0+
#595000000
1!
1+
#600000000
0!
0+
#605000000
1!
b0001 '
1(
1*
1+
b0001 1
12
14
b1 7
1;
1<
#610000000
0!
0+
#615000000
1!
1#
b1111111111111111 %
b1111111111111111 &
b0000 '
0(
0*
1+
1-
b1111111111111111 /
b1111111111111111 0
b0000 1
02
04
b1111111111111111 5
b1111111111111111 6
b0 7
b0 8
b0 9
0;
0<
#620000000
0!
0+
#625000000
1!
0#
1+
0-
b1 8
b1 9
#630000000
0!
0+
#635000000
1!
1+
b10 8
b10 9
#640000000
0!
0+
#645000000
1!
1+
b11 8
b11 9
#650000000
0!
0+
#655000000
1!
1+
b100 8
b100 9
#660000000
0!
0+
#665000000
1!
1+
b101 8
b101 9
#670000000
0!
0+
#675000000
1!
1+
b110 8
b110 9
#680000000
0!
0+
#685000000
1!
1+
b111 8
b111 9
#690000000
0!
0+
#695000000
1!
1+
b1000 8
b1000 9
#700000000
0!
0+
#705000000
1!
1+
b1001 8
b1001 9
#710000000
0!
0+
#715000000
1!
1+
b1010 8
b1010 9
#720000000
0!
0+
#725000000
1!
1+
b1011 8
b1011 9
#730000000
0!
0+
#735000000
1!
1+
b1100 8
b1100 9
#740000000
0!
0+
#745000000
1!
1+
b1101 8
b1101 9
#750000000
0!
0+
#755000000
1!
1+
b1110 8
b1110 9
#760000000
0!
0+
#765000000
1!
1+
b1111 8
b1111 9
#770000000
0!
0+
#775000000
1!
1+
b10000 8
#780000000
0!
0+
#785000000
1!
b1111 '
1(
1)
1+
b1111 1
12
13
b1111 7
1:
1<
