3-files/pattern_generator.vhd
LIBRARY ieee;
USE ieee.std_logic_1164.ALL;
USE ieee.numeric_std.ALL;

entity pattern_generator is
  GENERIC (
    LED_COUNT  : integer := 16;  -- larghezza del pattern
    CNT_WIDTH  : integer := 4    -- bit per rappresentare ones_count (0..8)
  );
  PORT (
    clk        : IN  std_logic;
    reset      : IN  std_logic;                                -- attivo alto
    enable     : IN  std_logic;                                -- genera nuovo pattern quando 1
    ones_count : IN  std_logic_vector(CNT_WIDTH-1 DOWNTO 0);   -- quanti 1 inserire (0..8)
    pattern    : OUT std_logic_vector(LED_COUNT-1 DOWNTO 0);   -- risultato
    done       : OUT std_logic                                 -- sale a '1' quando pronto
  );
end entity pattern_generator;

architecture Behavioral of pattern_generator is

  -- FSM states
  type state_type is (idle, load, shuffle, done_state);
  signal state       : state_type := idle;
  

  signal shuffle_pass : integer range 0 to 3 := 0;
  constant MAX_PASSES : integer := 2; -- fai 2 shuffle pass


  -- registro del pattern
  signal pattern_reg : std_logic_vector(LED_COUNT-1 DOWNTO 0) := (others => '0');
  -- LFSR per generazione numeri casuali
  signal lfsr        : std_logic_vector(LED_COUNT-1 DOWNTO 0) := (others => '1');
  -- contatore per lo shuffle (da LED_COUNT-1 downto 1)
  signal i_count     : integer range 0 to LED_COUNT-1 := 0;
  -- numero di 1 da inserire
  signal target_cnt  : integer range 0 to LED_COUNT := 0;
  -- flag interno di “done”
  signal done_int    : std_logic := '0';

begin

  -- esponi output
  pattern <= pattern_reg;
  done    <= done_int;

  process(clk, reset)
    variable temp_bit : std_logic;
    variable j_idx    : integer range 0 to LED_COUNT-1;
  begin
    if reset = '1' then
      state       <= idle;
      pattern_reg <= (others => '0');
      lfsr        <= (others => '1');
      i_count     <= 0;
      target_cnt  <= 0;
      done_int    <= '0';

    elsif rising_edge(clk) then
      case state is

        when idle =>
          done_int <= '0';
          if enable = '1' then
            -- cattura quanti 1 voglio (clamp a 0..LED_COUNT)
            if unsigned(ones_count) > LED_COUNT then
                target_cnt <= LED_COUNT;
              else
                target_cnt <= to_integer(unsigned(ones_count));
              end if;
            state      <= load;
          end if;

        when load =>
          -- carica inizialmente i primi target_cnt bit a '1', il resto a '0'
          for idx in 0 to LED_COUNT-1 loop
            if idx < target_cnt then
              pattern_reg(idx) <= '1';
            else
              pattern_reg(idx) <= '0';
            end if;
          end loop;
          i_count <= LED_COUNT - 1;
          state   <= shuffle;
          shuffle_pass <= 0;



        when shuffle =>
          -- aggiorna LFSR (x^16 + x^14 + 1) come esempio
          lfsr <= lfsr(LED_COUNT-2 DOWNTO 0) & (lfsr(LED_COUNT-1) XOR lfsr(LED_COUNT-3));

          -- scegli indice j tra 0 e i_count (inclusi)
          j_idx := to_integer(unsigned(lfsr(CNT_WIDTH-1 DOWNTO 0))) mod (i_count + 1);

          -- esegui swap tra posizione i_count e j_idx
          temp_bit               := pattern_reg(i_count);
          pattern_reg(i_count)   <= pattern_reg(j_idx);
          pattern_reg(j_idx)     <= temp_bit;

          -- check i_count && shuffle pass 
          if i_count = 0 then
            if shuffle_pass < MAX_PASSES - 1 then
              -- fai un altro giro di shuffle
              shuffle_pass <= shuffle_pass + 1;
              i_count      <= LED_COUNT - 1;
            else
              -- tutti i passaggi completati
              state <= done_state;
            end if;
          else
            i_count <= i_count - 1;
          end if;
          

        when done_state =>
          done_int <= '1';
          -- aspetta che enable torni a zero per nuovo trigger
          if enable = '0' then
            state <= idle;
          end if;

      end case;
    end if;
  end process;

end architecture Behavioral;

2-testbenches/tb_patt_gen.vhd
LIBRARY ieee;
USE ieee.std_logic_1164.ALL;
USE ieee.numeric_std.ALL;


ENTITY tb_pattern_generator IS
END tb_pattern_generator;

ARCHITECTURE behavior OF tb_pattern_generator IS
  -- Parametri del DUT
  CONSTANT LED_COUNT : integer := 16;
  CONSTANT CNT_WIDTH : integer := 4;

  -- Component declaration
  COMPONENT pattern_generator
    GENERIC (
      LED_COUNT : integer := LED_COUNT;
      CNT_WIDTH : integer := CNT_WIDTH
    );
    PORT (
      clk        : IN  std_logic;
      reset      : IN  std_logic;
      enable     : IN  std_logic;
      ones_count : IN  std_logic_vector(CNT_WIDTH-1 DOWNTO 0);
      pattern    : OUT std_logic_vector(LED_COUNT-1 DOWNTO 0);
      done       : OUT std_logic
    );
  END COMPONENT;

  -- Segnali di testbench
  SIGNAL clk_tb        : std_logic := '0';
  SIGNAL reset_tb      : std_logic := '1';
  SIGNAL enable_tb     : std_logic := '0';
  SIGNAL ones_count_tb : std_logic_vector(CNT_WIDTH-1 DOWNTO 0) := (OTHERS => '0');
  SIGNAL pattern_tb    : std_logic_vector(LED_COUNT-1 DOWNTO 0);
  SIGNAL done_tb       : std_logic;

  CONSTANT clk_period : time := 10 ns;

BEGIN
  -- Clock generator
  clk_process : PROCESS
  BEGIN
    LOOP
      clk_tb <= '0';
      WAIT FOR clk_period/2;
      clk_tb <= '1';
      WAIT FOR clk_period/2;
    END LOOP;
  END PROCESS;

  -- Instantiate DUT
  dut: pattern_generator
    GENERIC MAP (
      LED_COUNT => LED_COUNT,
      CNT_WIDTH => CNT_WIDTH
    )
    PORT MAP (
      clk        => clk_tb,
      reset      => reset_tb,
      enable     => enable_tb,
      ones_count => ones_count_tb,
      pattern    => pattern_tb,
      done       => done_tb
    );

  -- Stimulus process
  stim: PROCESS
  BEGIN
    -- Global reset
    reset_tb <= '1';
    WAIT FOR 50 ns;
    reset_tb <= '0';
    WAIT FOR 50 ns;

    -- Loop over values 6..8 for ones_count
    FOR i IN 6 TO 8 LOOP
      -- setta numero di 1
      ones_count_tb <= std_logic_vector(to_unsigned(i, CNT_WIDTH));
      -- generate new pattern
      enable_tb <= '1';
      WAIT FOR clk_period;
      enable_tb <= '0';

      -- aspetta la fine (done_tb = '1')
      WAIT UNTIL done_tb = '1';
      WAIT FOR 200 ns; -- lascia un po’ di tempo per osservare
    END LOOP;

    -- Fine simulazione
    report "Simulazione terminata.";
    assert false report "Stop simulazione." severity failure;

  END PROCESS;

END architecture behavior;

1-waves/patt_wave.vcd
$date
  Mon Apr 21 19:21:07 2025
$end
$version
  GHDL v0
$end
$timescale
  1 fs
$end
$scope module standard $end
$upscope $end
$scope module std_logic_1164 $end
$upscope $end
$scope module numeric_std $end
$upscope $end
$scope module tb_pattern_generator $end
$var reg 1 ! clk_tb $end
$var reg 1 " reset_tb $end
$var reg 1 # enable_tb $end
$var reg 4 $ ones_count_tb[3:0] $end
$var reg 16 % pattern_tb[15:0] $end
$var reg 1 & done_tb $end
$scope module dut $end
$var reg 1 ' clk $end
$var reg 1 ( reset $end
$var reg 1 ) enable $end
$var reg 4 * ones_count[3:0] $end
$var reg 16 + pattern[15:0] $end
$var reg 1 , done $end
$comment state is not handled $end
$var integer 32 - shuffle_pass $end
$var reg 16 . pattern_reg[15:0] $end
$var reg 16 / lfsr[15:0] $end
$var integer 32 0 i_count $end
$var integer 32 1 target_cnt $end
$var reg 1 2 done_int $end
$upscope $end
$upscope $end
$enddefinitions $end
#0
0!
1"
0#
b0000 $
b0000000000000000 %
0&
0'
1(
0)
b0000 *
b0000000000000000 +
0,
b0 -
b0000000000000000 .
b1111111111111111 /
b0 0
b0 1
02
#5000000
1!
1'
#10000000
0!
0'
#15000000
1!
1'
#20000000
0!
0'
#25000000
1!
1'
#30000000
0!
0'
#35000000
1!
1'
#40000000
0!
0'
#45000000
1!
1'
#50000000
0!
0"
0'
0(
#55000000
1!
1'
#60000000
0!
0'
#65000000
1!
1'
#70000000
0!
0'
#75000000
1!
1'
#80000000
0!
0'
#85000000
1!
1'
#90000000
0!
0'
#95000000
1!
1'
#100000000
0!
1#
b0110 $
0'
1)
b0110 *
#105000000
1!
1'
b110 1
#110000000
0!
0#
0'
0)
#115000000
1!
b0000000000111111 %
1'
b0000000000111111 +
b0000000000111111 .
b1111 0
#120000000
0!
0'
#125000000
1!
1'
b1111111111111110 /
b1110 0
#130000000
0!
0'
#135000000
1!
1'
b1111111111111100 /
b1101 0
#140000000
0!
0'
#145000000
1!
1'
b1111111111111000 /
b1100 0
#150000000
0!
0'
#155000000
1!
1'
b1111111111110000 /
b1011 0
#160000000
0!
0'
#165000000
1!
b0000100000111110 %
1'
b0000100000111110 +
b0000100000111110 .
b1111111111100000 /
b1010 0
#170000000
0!
0'
#175000000
1!
1'
b1111111111000000 /
b1001 0
#180000000
0!
0'
#185000000
1!
1'
b1111111110000000 /
b1000 0
#190000000
0!
0'
#195000000
1!
1'
b1111111100000000 /
b111 0
#200000000
0!
0'
#205000000
1!
1'
b1111111000000000 /
b110 0
#210000000
0!
0'
#215000000
1!
1'
b1111110000000000 /
b101 0
#220000000
0!
0'
#225000000
1!
b0000100000011111 %
1'
b0000100000011111 +
b0000100000011111 .
b1111100000000000 /
b100 0
#230000000
0!
0'
#235000000
1!
1'
b1111000000000000 /
b11 0
#240000000
0!
0'
#245000000
1!
1'
b1110000000000000 /
b10 0
#250000000
0!
0'
#255000000
1!
1'
b1100000000000000 /
b1 0
#260000000
0!
0'
#265000000
1!
1'
b1000000000000001 /
b0 0
#270000000
0!
0'
#275000000
1!
1'
b1 -
b0000000000000011 /
b1111 0
#280000000
0!
0'
#285000000
1!
b1000100000010111 %
1'
b1000100000010111 +
b1000100000010111 .
b0000000000000110 /
b1110 0
#290000000
0!
0'
#295000000
1!
1'
b0000000000001100 /
b1101 0
#300000000
0!
0'
#305000000
1!
1'
b0000000000011000 /
b1100 0
#310000000
0!
0'
#315000000
1!
1'
b0000000000110000 /
b1011 0
#320000000
0!
0'
#325000000
1!
1'
b0000000001100000 /
b1010 0
#330000000
0!
0'
#335000000
1!
b1000110000010110 %
1'
b1000110000010110 +
b1000110000010110 .
b0000000011000000 /
b1001 0
#340000000
0!
0'
#345000000
1!
1'
b0000000110000000 /
b1000 0
#350000000
0!
0'
#355000000
1!
1'
b0000001100000000 /
b111 0
#360000000
0!
0'
#365000000
1!
1'
b0000011000000000 /
b110 0
#370000000
0!
0'
#375000000
1!
1'
b0000110000000000 /
b101 0
#380000000
0!
0'
#385000000
1!
1'
b0001100000000000 /
b100 0
#390000000
0!
0'
#395000000
1!
b1000110000000111 %
1'
b1000110000000111 +
b1000110000000111 .
b0011000000000000 /
b11 0
#400000000
0!
0'
#405000000
1!
b1000110000001110 %
1'
b1000110000001110 +
b1000110000001110 .
b0110000000000001 /
b10 0
#410000000
0!
0'
#415000000
1!
1'
b1100000000000011 /
b1 0
#420000000
0!
0'
#425000000
1!
1'
b1000000000000111 /
b0 0
#430000000
0!
0'
#435000000
1!
1'
b0000000000001111 /
#440000000
0!
0'
#445000000
1!
1&
1'
1,
12
#450000000
0!
0'
#455000000
1!
0&
1'
0,
02
#460000000
0!
0'
#465000000
1!
1'
#470000000
0!
0'
#475000000
1!
1'
#480000000
0!
0'
#485000000
1!
1'
#490000000
0!
0'
#495000000
1!
1'
#500000000
0!
0'
#505000000
1!
1'
#510000000
0!
0'
#515000000
1!
1'
#520000000
0!
0'
#525000000
1!
1'
#530000000
0!
0'
#535000000
1!
1'
#540000000
0!
0'
#545000000
1!
1'
#550000000
0!
0'
#555000000
1!
1'
#560000000
0!
0'
#565000000
1!
1'
#570000000
0!
0'
#575000000
1!
1'
#580000000
0!
0'
#585000000
1!
1'
#590000000
0!
0'
#595000000
1!
1'
#600000000
0!
0'
#605000000
1!
1'
#610000000
0!
0'
#615000000
1!
1'
#620000000
0!
0'
#625000000
1!
1'
#630000000
0!
0'
#635000000
1!
1'
#640000000
0!
0'
#645000000
1!
1#
b0111 $
1'
1)
b0111 *
b111 1
#650000000
0!
0'
#655000000
1!
0#
b0000000001111111 %
1'
0)
b0000000001111111 +
b0 -
b0000000001111111 .
b1111 0
#660000000
0!
0'
#665000000
1!
1'
b0000000000011110 /
b1110 0
#670000000
0!
0'
#675000000
1!
1'
b0000000000111100 /
b1101 0
#680000000
0!
0'
#685000000
1!
1'
b0000000001111000 /
b1100 0
#690000000
0!
0'
#695000000
1!
1'
b0000000011110000 /
b1011 0
#700000000
0!
0'
#705000000
1!
b0000100001111110 %
1'
b0000100001111110 +
b0000100001111110 .
b0000000111100000 /
b1010 0
#710000000
0!
0'
#715000000
1!
1'
b0000001111000000 /
b1001 0
#720000000
0!
0'
#725000000
1!
1'
b0000011110000000 /
b1000 0
#730000000
0!
0'
#735000000
1!
1'
b0000111100000000 /
b111 0
#740000000
0!
0'
#745000000
1!
1'
b0001111000000000 /
b110 0
#750000000
0!
0'
#755000000
1!
b0000100000111111 %
1'
b0000100000111111 +
b0000100000111111 .
b0011110000000000 /
b101 0
#760000000
0!
0'
#765000000
1!
1'
b0111100000000001 /
b100 0
#770000000
0!
0'
#775000000
1!
1'
b1111000000000011 /
b11 0
#780000000
0!
0'
#785000000
1!
1'
b1110000000000110 /
b10 0
#790000000
0!
0'
#795000000
1!
1'
b1100000000001100 /
b1 0
#800000000
0!
0'
#805000000
1!
1'
b1000000000011001 /
b0 0
#810000000
0!
0'
#815000000
1!
1'
b1 -
b0000000000110011 /
b1111 0
#820000000
0!
0'
#825000000
1!
b1000100000110111 %
1'
b1000100000110111 +
b1000100000110111 .
b0000000001100110 /
b1110 0
#830000000
0!
0'
#835000000
1!
1'
b0000000011001100 /
b1101 0
#840000000
0!
0'
#845000000
1!
1'
b0000000110011000 /
b1100 0
#850000000
0!
0'
#855000000
1!
1'
b0000001100110000 /
b1011 0
#860000000
0!
0'
#865000000
1!
1'
b0000011001100000 /
b1010 0
#870000000
0!
0'
#875000000
1!
b1000110000110110 %
1'
b1000110000110110 +
b1000110000110110 .
b0000110011000000 /
b1001 0
#880000000
0!
0'
#885000000
1!
1'
b0001100110000000 /
b1000 0
#890000000
0!
0'
#895000000
1!
1'
b0011001100000000 /
b111 0
#900000000
0!
0'
#905000000
1!
1'
b0110011000000001 /
b110 0
#910000000
0!
0'
#915000000
1!
b1000110001110100 %
1'
b1000110001110100 +
b1000110001110100 .
b1100110000000011 /
b101 0
#920000000
0!
0'
#925000000
1!
b1000110001011100 %
1'
b1000110001011100 +
b1000110001011100 .
b1001100000000111 /
b100 0
#930000000
0!
0'
#935000000
1!
1'
b0011000000001111 /
b11 0
#940000000
0!
0'
#945000000
1!
1'
b0110000000011111 /
b10 0
#950000000
0!
0'
#955000000
1!
b1000110001011001 %
1'
b1000110001011001 +
b1000110001011001 .
b1100000000111111 /
b1 0
#960000000
0!
0'
#965000000
1!
1'
b1000000001111111 /
b0 0
#970000000
0!
0'
#975000000
1!
1'
b0000000011111111 /
#980000000
0!
0'
#985000000
1!
1&
1'
1,
12
#990000000
0!
0'
#995000000
1!
0&
1'
0,
02
#1000000000
0!
0'
#1005000000
1!
1'
#1010000000
0!
0'
#1015000000
1!
1'
#1020000000
0!
0'
#1025000000
1!
1'
#1030000000
0!
0'
#1035000000
1!
1'
#1040000000
0!
0'
#1045000000
1!
1'
#1050000000
0!
0'
#1055000000
1!
1'
#1060000000
0!
0'
#1065000000
1!
1'
#1070000000
0!
0'
#1075000000
1!
1'
#1080000000
0!
0'
#1085000000
1!
1'
#1090000000
0!
0'
#1095000000
1!
1'
#1100000000
0!
0'
#1105000000
1!
1'
#1110000000
0!
0'
#1115000000
1!
1'
#1120000000
0!
0'
#1125000000
1!
1'
#1130000000
0!
0'
#1135000000
1!
1'
#1140000000
0!
0'
#1145000000
1!
1'
#1150000000
0!
0'
#1155000000
1!
1'
#1160000000
0!
0'
#1165000000
1!
1'
#1170000000
0!
0'
#1175000000
1!
1'
#1180000000
0!
0'
#1185000000
1!
1#
b1000 $
1'
1)
b1000 *
b1000 1
#1190000000
0!
0'
#1195000000
1!
0#
b0000000011111111 %
1'
0)
b0000000011111111 +
b0 -
b0000000011111111 .
b1111 0
#1200000000
0!
0'
#1205000000
1!
1'
b0000000111111110 /
b1110 0
#1210000000
0!
0'
#1215000000
1!
1'
b0000001111111100 /
b1101 0
#1220000000
0!
0'
#1225000000
1!
1'
b0000011111111000 /
b1100 0
#1230000000
0!
0'
#1235000000
1!
1'
b0000111111110000 /
b1011 0
#1240000000
0!
0'
#1245000000
1!
b0000100011111110 %
1'
b0000100011111110 +
b0000100011111110 .
b0001111111100000 /
b1010 0
#1250000000
0!
0'
#1255000000
1!
1'
b0011111111000000 /
b1001 0
#1260000000
0!
0'
#1265000000
1!
1'
b0111111110000001 /
b1000 0
#1270000000
0!
0'
#1275000000
1!
b0000100111111100 %
1'
b0000100111111100 +
b0000100111111100 .
b1111111100000011 /
b111 0
#1280000000
0!
0'
#1285000000
1!
1'
b1111111000000110 /
b110 0
#1290000000
0!
0'
#1295000000
1!
1'
b1111110000001100 /
b101 0
#1300000000
0!
0'
#1305000000
1!
b0000100111011101 %
1'
b0000100111011101 +
b0000100111011101 .
b1111100000011000 /
b100 0
#1310000000
0!
0'
#1315000000
1!
1'
b1111000000110000 /
b11 0
#1320000000
0!
0'
#1325000000
1!
1'
b1110000001100000 /
b10 0
#1330000000
0!
0'
#1335000000
1!
1'
b1100000011000000 /
b1 0
#1340000000
0!
0'
#1345000000
1!
b0000100111011110 %
1'
b0000100111011110 +
b0000100111011110 .
b1000000110000001 /
b0 0
#1350000000
0!
0'
#1355000000
1!
1'
b1 -
b0000001100000011 /
b1111 0
#1360000000
0!
0'
#1365000000
1!
b1000100111010110 %
1'
b1000100111010110 +
b1000100111010110 .
b0000011000000110 /
b1110 0
#1370000000
0!
0'
#1375000000
1!
b1100100110010110 %
1'
b1100100110010110 +
b1100100110010110 .
b0000110000001100 /
b1101 0
#1380000000
0!
0'
#1385000000
1!
1'
b0001100000011000 /
b1100 0
#1390000000
0!
0'
#1395000000
1!
b1101100010010110 %
1'
b1101100010010110 +
b1101100010010110 .
b0011000000110000 /
b1011 0
#1400000000
0!
0'
#1405000000
1!
b1101000010010111 %
1'
b1101000010010111 +
b1101000010010111 .
b0110000001100001 /
b1010 0
#1410000000
0!
0'
#1415000000
1!
b1101010010010101 %
1'
b1101010010010101 +
b1101010010010101 .
b1100000011000011 /
b1001 0
#1420000000
0!
0'
#1425000000
1!
1'
b1000000110000111 /
b1000 0
#1430000000
0!
0'
#1435000000
1!
b1101010100010101 %
1'
b1101010100010101 +
b1101010100010101 .
b0000001100001111 /
b111 0
#1440000000
0!
0'
#1445000000
1!
1'
b0000011000011110 /
b110 0
#1450000000
0!
0'
#1455000000
1!
b1101010101010100 %
1'
b1101010101010100 +
b1101010101010100 .
b0000110000111100 /
b101 0
#1460000000
0!
0'
#1465000000
1!
1'
b0001100001111000 /
b100 0
#1470000000
0!
0'
#1475000000
1!
b1101010101001100 %
1'
b1101010101001100 +
b1101010101001100 .
b0011000011110000 /
b11 0
#1480000000
0!
0'
#1485000000
1!
b1101010101000101 %
1'
b1101010101000101 +
b1101010101000101 .
b0110000111100001 /
b10 0
#1490000000
0!
0'
#1495000000
1!
b1101010101000011 %
1'
b1101010101000011 +
b1101010101000011 .
b1100001111000011 /
b1 0
#1500000000
0!
0'
#1505000000
1!
1'
b1000011110000111 /
b0 0
#1510000000
0!
0'
#1515000000
1!
1'
b0000111100001111 /
#1520000000
0!
0'
#1525000000
1!
1&
1'
1,
12
#1530000000
0!
0'
#1535000000
1!
0&
1'
0,
02
